LICENSE
MANIFEST.in
README
setup.py
divebomb/DeepDive.py
divebomb/Dive.py
divebomb/__init__.py
divebomb/plotting.py
divebomb/preprocessing.py
divebomb.egg-info/PKG-INFO
divebomb.egg-info/SOURCES.txt
divebomb.egg-info/dependency_links.txt
divebomb.egg-info/requires.txt
divebomb.egg-info/top_level.txt