Metadata-Version: 2.1
Name: divebomb
Version: 1.1.2
Summary: divebomb dive classification algorithm
Home-page: https://github.com/ocean-tracking-network/divebomb
Author: Alex Nunes
Author-email: alex.et.nunes@gmail.com
License: GPLv2
Download-URL: https://github.com/ocean-tracking-network/divebomb
Platform: UNKNOWN
Classifier: Natural Language :: English
Classifier: Operating System :: OS Independent
Classifier: Programming Language :: Python
Classifier: Programming Language :: Python :: 2.7
Classifier: Programming Language :: Python :: 3.5
Classifier: Programming Language :: Python :: 3.6
Classifier: Programming Language :: Python :: 3.7
